jk_sysinfo/__init__.py
jk_sysinfo/get_accesspoints.py
jk_sysinfo/get_apt_list_upgradable.py
jk_sysinfo/get_bios_info.py
jk_sysinfo/get_cpu_info.py
jk_sysinfo/get_date.py
jk_sysinfo/get_df.py
jk_sysinfo/get_dmi_decode.py
jk_sysinfo/get_docker_stats.py
jk_sysinfo/get_dpkg_list.py
jk_sysinfo/get_etc_group.py
jk_sysinfo/get_etc_hostname.py
jk_sysinfo/get_etc_os_release.py
jk_sysinfo/get_etc_passwd.py
jk_sysinfo/get_hdparm_I.py
jk_sysinfo/get_ifconfig.py
jk_sysinfo/get_lsb_release_a.py
jk_sysinfo/get_lsblk.py
jk_sysinfo/get_lshw.py
jk_sysinfo/get_motherboard_info.py
jk_sysinfo/get_mount.py
jk_sysinfo/get_needs_reboot.py
jk_sysinfo/get_net_info.py
jk_sysinfo/get_pip3_list.py
jk_sysinfo/get_proc_cpu_info.py
jk_sysinfo/get_proc_load_avg.py
jk_sysinfo/get_proc_meminfo.py
jk_sysinfo/get_ps.py
jk_sysinfo/get_ps_local.py
jk_sysinfo/get_sensors.py
jk_sysinfo/get_systemctl_units.py
jk_sysinfo/get_uptime.py
jk_sysinfo/get_user_info.py
jk_sysinfo/get_vcgencmd.py
jk_sysinfo/invoke_utils.py
jk_sysinfo/parsing_utils.py
jk_sysinfo/value_formatting.py
jk_sysinfo/OLD/get_apt_list.py.old
jk_sysinfo/OLD/get_os_data.py
jk_sysinfo/bin/cli_sysinfo.py
jk_sysinfo/bin/cli_sysinfo_json.py
jk_sysinfo/cli/ServerCfg.py
jk_sysinfo/cli/__init__.py
jk_sysinfo/entity/DriveInfo.py
jk_sysinfo/entity/DrivePartitionInfo.py
jk_sysinfo/entity/__init__.py
jk_sysinfo-0.2024.9.18.3.dist-info/entry_points.txt
jk_sysinfo-0.2024.9.18.3.dist-info/WHEEL
jk_sysinfo-0.2024.9.18.3.dist-info/METADATA
jk_sysinfo-0.2024.9.18.3.dist-info/RECORD
