Metadata-Version: 2.1
Name: jk_sysinfo
Version: 0.2024.9.18.3
Summary: This python module provides ways to retrieve and parse technical system data of Linux computer systems.
Keywords: monitoring,os
Author-email: Jürgen Knauth <pubsrc@binary-overflow.de>
Maintainer-email: Jürgen Knauth <pubsrc@binary-overflow.de>
Requires-Python: >=3.8
Classifier: Development Status :: 3 - Alpha
Classifier: License :: OSI Approved :: Apache Software License
Classifier: Programming Language :: Python :: 3
Classifier: Topic :: System :: Monitoring
Requires-Dist: python-dateutil
Requires-Dist: fabric
Requires-Dist: pytz
Requires-Dist: jk_console
Requires-Dist: jk_typing
Requires-Dist: jk_version
Requires-Dist: jk_cachefunccalls
Requires-Dist: jk_argparsing
Requires-Dist: jk_etcpasswd
Requires-Dist: jk_cmdoutputparsinghelper
Requires-Dist: jk_json
Requires-Dist: jk_flexdata
Requires-Dist: jk_logging
Requires-Dist: jk_pwdinput
